[
    {
        "inputs": [
            {
                "internalType": "address",
                "name": "_BTBTokenAddress",
                "type": "address"
            },
            {
                "internalType": "address",
                "name": "initialOwner",
                "type": "address"
            }
        ],
        "stateMutability": "nonpayable",
        "type": "constructor"
    },
    {
        "inputs": [
            {
                "internalType": "address",
                "name": "owner",
                "type": "address"
            }
        ],
        "name": "OwnableInvalidOwner",
        "type": "error"
    },
    {
        "inputs": [
            {
                "internalType": "address",
                "name": "account",
                "type": "address"
            }
        ],
        "name": "OwnableUnauthorizedAccount",
        "type": "error"
    },
    {
        "anonymous": false,
        "inputs": [
            {
                "indexed": true,
                "internalType": "address",
                "name": "previousOwner",
                "type": "address"
            },
            {
                "indexed": true,
                "internalType": "address",
                "name": "newOwner",
                "type": "address"
            }
        ],
        "name": "OwnershipTransferred",
        "type": "event"
    },
    {
        "anonymous": false,
        "inputs": [
            {
                "indexed": false,
                "internalType": "address",
                "name": "account",
                "type": "address"
            }
        ],
        "name": "Paused",
        "type": "event"
    },
    {
        "anonymous": false,
        "inputs": [
            {
                "indexed": true,
                "internalType": "address",
                "name": "user",
                "type": "address"
            },
            {
                "indexed": false,
                "internalType": "uint256",
                "name": "reward",
                "type": "uint256"
            }
        ],
        "name": "RewardClaimed",
        "type": "event"
    },
    {
        "anonymous": false,
        "inputs": [
            {
                "indexed": true,
                "internalType": "address",
                "name": "user",
                "type": "address"
            },
            {
                "indexed": false,
                "internalType": "uint256",
                "name": "amount",
                "type": "uint256"
            },
            {
                "indexed": true,
                "internalType": "address",
                "name": "referrer",
                "type": "address"
            }
        ],
        "name": "Staked",
        "type": "event"
    },
    {
        "anonymous": false,
        "inputs": [
            {
                "indexed": false,
                "internalType": "address",
                "name": "account",
                "type": "address"
            }
        ],
        "name": "Unpaused",
        "type": "event"
    },
    {
        "anonymous": false,
        "inputs": [
            {
                "indexed": true,
                "internalType": "address",
                "name": "user",
                "type": "address"
            },
            {
                "indexed": false,
                "internalType": "uint256",
                "name": "amount",
                "type": "uint256"
            }
        ],
        "name": "Withdrawn",
        "type": "event"
    },
    {
        "inputs": [],
        "name": "BTBToken",
        "outputs": [
            {
                "internalType": "contract IERC20",
                "name": "",
                "type": "address"
            }
        ],
        "stateMutability": "view",
        "type": "function"
    },
    {
        "inputs": [],
        "name": "FEE_PERCENTAGE",
        "outputs": [
            {
                "internalType": "uint256",
                "name": "",
                "type": "uint256"
            }
        ],
        "stateMutability": "view",
        "type": "function"
    },
    {
        "inputs": [],
        "name": "STAKE_AMOUNT",
        "outputs": [
            {
                "internalType": "uint256",
                "name": "",
                "type": "uint256"
            }
        ],
        "stateMutability": "view",
        "type": "function"
    },
    {
        "inputs": [
            {
                "internalType": "address",
                "name": "user",
                "type": "address"
            }
        ],
        "name": "checkUserBalance",
        "outputs": [
            {
                "internalType": "uint256",
                "name": "",
                "type": "uint256"
            }
        ],
        "stateMutability": "view",
        "type": "function"
    },
    {
        "inputs": [],
        "name": "claimReward",
        "outputs": [],
        "stateMutability": "nonpayable",
        "type": "function"
    },
    {
        "inputs": [],
        "name": "getFeePercentage",
        "outputs": [
            {
                "internalType": "uint256",
                "name": "",
                "type": "uint256"
            }
        ],
        "stateMutability": "pure",
        "type": "function"
    },
    {
        "inputs": [
            {
                "internalType": "address",
                "name": "user",
                "type": "address"
            }
        ],
        "name": "getReferralCount",
        "outputs": [
            {
                "internalType": "uint256",
                "name": "",
                "type": "uint256"
            }
        ],
        "stateMutability": "view",
        "type": "function"
    },
    {
        "inputs": [
            {
                "internalType": "address",
                "name": "user",
                "type": "address"
            }
        ],
        "name": "getReferrer",
        "outputs": [
            {
                "internalType": "address",
                "name": "",
                "type": "address"
            }
        ],
        "stateMutability": "view",
        "type": "function"
    },
    {
        "inputs": [],
        "name": "getTotalStaked",
        "outputs": [
            {
                "internalType": "uint256",
                "name": "",
                "type": "uint256"
            }
        ],
        "stateMutability": "view",
        "type": "function"
    },
    {
        "inputs": [
            {
                "internalType": "address",
                "name": "user",
                "type": "address"
            }
        ],
        "name": "getUserInvestedBalance",
        "outputs": [
            {
                "internalType": "uint256",
                "name": "",
                "type": "uint256"
            }
        ],
        "stateMutability": "view",
        "type": "function"
    },
    {
        "inputs": [
            {
                "internalType": "address",
                "name": "user",
                "type": "address"
            }
        ],
        "name": "getUserStakedAmount",
        "outputs": [
            {
                "internalType": "uint256",
                "name": "",
                "type": "uint256"
            }
        ],
        "stateMutability": "view",
        "type": "function"
    },
    {
        "inputs": [
            {
                "internalType": "address",
                "name": "user",
                "type": "address"
            }
        ],
        "name": "isRewardClaimed",
        "outputs": [
            {
                "internalType": "bool",
                "name": "",
                "type": "bool"
            }
        ],
        "stateMutability": "view",
        "type": "function"
    },
    {
        "inputs": [],
        "name": "owner",
        "outputs": [
            {
                "internalType": "address",
                "name": "",
                "type": "address"
            }
        ],
        "stateMutability": "view",
        "type": "function"
    },
    {
        "inputs": [],
        "name": "paused",
        "outputs": [
            {
                "internalType": "bool",
                "name": "",
                "type": "bool"
            }
        ],
        "stateMutability": "view",
        "type": "function"
    },
    {
        "inputs": [
            {
                "internalType": "address",
                "name": "",
                "type": "address"
            }
        ],
        "name": "refCount",
        "outputs": [
            {
                "internalType": "uint256",
                "name": "",
                "type": "uint256"
            }
        ],
        "stateMutability": "view",
        "type": "function"
    },
    {
        "inputs": [
            {
                "internalType": "address",
                "name": "",
                "type": "address"
            }
        ],
        "name": "referrals",
        "outputs": [
            {
                "internalType": "address",
                "name": "",
                "type": "address"
            }
        ],
        "stateMutability": "view",
        "type": "function"
    },
    {
        "inputs": [],
        "name": "renounceOwnership",
        "outputs": [],
        "stateMutability": "nonpayable",
        "type": "function"
    },
    {
        "inputs": [
            {
                "internalType": "address",
                "name": "tokenAddress",
                "type": "address"
            },
            {
                "internalType": "uint256",
                "name": "amount",
                "type": "uint256"
            }
        ],
        "name": "rescueTokens",
        "outputs": [],
        "stateMutability": "nonpayable",
        "type": "function"
    },
    {
        "inputs": [
            {
                "internalType": "address",
                "name": "",
                "type": "address"
            }
        ],
        "name": "rewardClaimed",
        "outputs": [
            {
                "internalType": "bool",
                "name": "",
                "type": "bool"
            }
        ],
        "stateMutability": "view",
        "type": "function"
    },
    {
        "inputs": [
            {
                "internalType": "address",
                "name": "referrer",
                "type": "address"
            }
        ],
        "name": "stake",
        "outputs": [],
        "stateMutability": "nonpayable",
        "type": "function"
    },
    {
        "inputs": [
            {
                "internalType": "address",
                "name": "",
                "type": "address"
            }
        ],
        "name": "stakes",
        "outputs": [
            {
                "internalType": "uint256",
                "name": "",
                "type": "uint256"
            }
        ],
        "stateMutability": "view",
        "type": "function"
    },
    {
        "inputs": [],
        "name": "stakingPaused",
        "outputs": [
            {
                "internalType": "bool",
                "name": "",
                "type": "bool"
            }
        ],
        "stateMutability": "view",
        "type": "function"
    },
    {
        "inputs": [],
        "name": "togglePause",
        "outputs": [],
        "stateMutability": "nonpayable",
        "type": "function"
    },
    {
        "inputs": [],
        "name": "toggleStakingPause",
        "outputs": [],
        "stateMutability": "nonpayable",
        "type": "function"
    },
    {
        "inputs": [
            {
                "internalType": "address",
                "name": "newOwner",
                "type": "address"
            }
        ],
        "name": "transferOwnership",
        "outputs": [],
        "stateMutability": "nonpayable",
        "type": "function"
    },
    {
        "inputs": [],
        "name": "withdrawStake",
        "outputs": [],
        "stateMutability": "nonpayable",
        "type": "function"
    },
    {
        "inputs": [
            {
                "internalType": "uint256",
                "name": "amount",
                "type": "uint256"
            }
        ],
        "name": "withdrawTokens",
        "outputs": [],
        "stateMutability": "nonpayable",
        "type": "function"
    }
]